{
    "부산광역시": [
        {
            "SDID": 2600,
            "SDNAME": "부산광역시",
            "SGGID": "0",
            "SGGNAME": "합계",
            "WIWID": 0,
            "WIWNAME": "합계",
            "SUNSU": "2,857,335",
            "TUSU": "1,611,216",
            "TUYUL": "56.4",
            "data": [
                {
                    "name": "더불어민주당",
                    "value": 7,
                    "itemStyle": {
                        "color": "#152484"
                    }
                },
                {
                    "name": "국민의힘",
                    "value": 9,
                    "itemStyle": {
                        "color": "#E61E2B"
                    }
                }
            ]
        },
        {
            "SDID": 2600,
            "SDNAME": "부산광역시",
            "SGGID": "4260100",
            "SGGNAME": "중구",
            "WIWID": 2601,
            "WIWNAME": "중구",
            "SUNSU": "34,767",
            "TUSU": "20,551",
            "TUYUL": "59.1",
            "GPYUL": "100.0%",
            "name": 2601,
            "nametxt": "중구",
            "data": [
                {
                    "value": 42.13,
                    "name": "강희은",
                    "party": "더불어민주당",
                    "pyo": 8456,
                    "itemStyle": {
                        "color": "#152484"
                    }
                },
                {
                    "value": 57.86,
                    "name": "최진봉",
                    "party": "국민의힘",
                    "pyo": 11612,
                    "itemStyle": {
                        "color": "#E61E2B"
                    }
                }
            ],
            "HUBO01": "강희은",
            "JD01": "더불어민주당",
            "DUGSU01": "8,456",
            "DUGYUL01": "42.13",
            "HUBO02": "최진봉",
            "JD02": "국민의힘",
            "DUGSU02": "11,612",
            "DUGYUL02": "57.86",
            "WINNUM": 2,
            "WINDUGSU": "11,612",
            "WINDUGYUL": "57.86",
            "WINHUBO": "최진봉",
            "WINJD": "국민의힘",
            "SECNUM": 1,
            "SECDUGSU": "8,456",
            "SECDUGYUL": "42.13",
            "SECHUBO": "강희은",
            "SECJD": "더불어민주당",
            "DUGYULCHA": "15.73",
            "DUGSUCHA": "3,156",
            "value": 2
        },
        {
            "SDID": 2600,
            "SDNAME": "부산광역시",
            "SGGID": "4260200",
            "SGGNAME": "서구",
            "WIWID": 2602,
            "WIWNAME": "서구",
            "SUNSU": "91,856",
            "TUSU": "56,476",
            "TUYUL": "61.5",
            "GPYUL": "99.98%",
            "name": 2602,
            "nametxt": "서구",
            "data": [
                {
                    "value": 43.27,
                    "name": "황정재",
                    "party": "더불어민주당",
                    "pyo": 23988,
                    "itemStyle": {
                        "color": "#152484"
                    }
                },
                {
                    "value": 56.72,
                    "name": "공한수",
                    "party": "국민의힘",
                    "pyo": 31447,
                    "itemStyle": {
                        "color": "#E61E2B"
                    }
                }
            ],
            "HUBO01": "황정재",
            "JD01": "더불어민주당",
            "DUGSU01": "23,988",
            "DUGYUL01": "43.27",
            "HUBO02": "공한수",
            "JD02": "국민의힘",
            "DUGSU02": "31,447",
            "DUGYUL02": "56.72",
            "WINNUM": 2,
            "WINDUGSU": "31,447",
            "WINDUGYUL": "56.72",
            "WINHUBO": "공한수",
            "WINJD": "국민의힘",
            "SECNUM": 1,
            "SECDUGSU": "23,988",
            "SECDUGYUL": "43.27",
            "SECHUBO": "황정재",
            "SECJD": "더불어민주당",
            "DUGYULCHA": "13.45",
            "DUGSUCHA": "7,459",
            "value": 2
        },
        {
            "SDID": 2600,
            "SDNAME": "부산광역시",
            "SGGID": "4260300",
            "SGGNAME": "동구",
            "WIWID": 2603,
            "WIWNAME": "동구",
            "SUNSU": "76,810",
            "TUSU": "47,031",
            "TUYUL": "61.2",
            "GPYUL": "99.91%",
            "name": 2603,
            "nametxt": "동구",
            "data": [
                {
                    "value": 48.96,
                    "name": "김종우",
                    "party": "더불어민주당",
                    "pyo": 22479,
                    "itemStyle": {
                        "color": "#152484"
                    }
                },
                {
                    "value": 51.03,
                    "name": "강철호",
                    "party": "국민의힘",
                    "pyo": 23433,
                    "itemStyle": {
                        "color": "#E61E2B"
                    }
                }
            ],
            "HUBO01": "김종우",
            "JD01": "더불어민주당",
            "DUGSU01": "22,479",
            "DUGYUL01": "48.96",
            "HUBO02": "강철호",
            "JD02": "국민의힘",
            "DUGSU02": "23,433",
            "DUGYUL02": "51.03",
            "WINNUM": 2,
            "WINDUGSU": "23,433",
            "WINDUGYUL": "51.03",
            "WINHUBO": "강철호",
            "WINJD": "국민의힘",
            "SECNUM": 1,
            "SECDUGSU": "22,479",
            "SECDUGYUL": "48.96",
            "SECHUBO": "김종우",
            "SECJD": "더불어민주당",
            "DUGYULCHA": "2.07",
            "DUGSUCHA": "954",
            "value": 2
        },
        {
            "SDID": 2600,
            "SDNAME": "부산광역시",
            "SGGID": "4260400",
            "SGGNAME": "영도구",
            "WIWID": 2604,
            "WIWNAME": "영도구",
            "SUNSU": "92,438",
            "TUSU": "42,256",
            "TUYUL": "45.7",
            "GPYUL": "75.66%",
            "name": 2604,
            "nametxt": "영도구",
            "data": [
                {
                    "value": 52.51,
                    "name": "김철훈",
                    "party": "더불어민주당",
                    "pyo": 21703,
                    "itemStyle": {
                        "color": "#152484"
                    }
                },
                {
                    "value": 37.52,
                    "name": "안성민",
                    "party": "국민의힘",
                    "pyo": 15508,
                    "itemStyle": {
                        "color": "#E61E2B"
                    }
                },
                {
                    "value": 9.96,
                    "name": "김기재",
                    "party": "무소속",
                    "pyo": 4117,
                    "itemStyle": {
                        "color": "#8b8b8b"
                    }
                }
            ],
            "HUBO01": "김철훈",
            "JD01": "더불어민주당",
            "DUGSU01": "21,703",
            "DUGYUL01": "52.51",
            "HUBO02": "안성민",
            "JD02": "국민의힘",
            "DUGSU02": "15,508",
            "DUGYUL02": "37.52",
            "HUBO03": "김기재",
            "JD03": "무소속",
            "DUGSU03": "4,117",
            "DUGYUL03": "9.96",
            "WINNUM": 1,
            "WINDUGSU": "21,703",
            "WINDUGYUL": "52.51",
            "WINHUBO": "김철훈",
            "WINJD": "더불어민주당",
            "SECNUM": 2,
            "SECDUGSU": "15,508",
            "SECDUGYUL": "37.52",
            "SECHUBO": "안성민",
            "SECJD": "국민의힘",
            "DUGYULCHA": "14.99",
            "DUGSUCHA": "6,195",
            "value": 1
        },
        {
            "SDID": 2600,
            "SDNAME": "부산광역시",
            "SGGID": "4260500",
            "SGGNAME": "부산진구",
            "WIWID": 2605,
            "WIWNAME": "부산진구",
            "SUNSU": "327,585",
            "TUSU": "172,443",
            "TUYUL": "52.6",
            "GPYUL": "87.45%",
            "name": 2605,
            "nametxt": "부산진구",
            "data": [
                {
                    "value": 47.08,
                    "name": "서은숙",
                    "party": "더불어민주당",
                    "pyo": 79519,
                    "itemStyle": {
                        "color": "#152484"
                    }
                },
                {
                    "value": 52.91,
                    "name": "김영욱",
                    "party": "국민의힘",
                    "pyo": 89379,
                    "itemStyle": {
                        "color": "#E61E2B"
                    }
                }
            ],
            "HUBO01": "서은숙",
            "JD01": "더불어민주당",
            "DUGSU01": "79,519",
            "DUGYUL01": "47.08",
            "HUBO02": "김영욱",
            "JD02": "국민의힘",
            "DUGSU02": "89,379",
            "DUGYUL02": "52.91",
            "WINNUM": 2,
            "WINDUGSU": "89,379",
            "WINDUGYUL": "52.91",
            "WINHUBO": "김영욱",
            "WINJD": "국민의힘",
            "SECNUM": 1,
            "SECDUGSU": "79,519",
            "SECDUGYUL": "47.08",
            "SECHUBO": "서은숙",
            "SECJD": "더불어민주당",
            "DUGYULCHA": "5.83",
            "DUGSUCHA": "9,860",
            "value": 2
        },
        {
            "SDID": 2600,
            "SDNAME": "부산광역시",
            "SGGID": "4260600",
            "SGGNAME": "동래구",
            "WIWID": 2606,
            "WIWNAME": "동래구",
            "SUNSU": "233,401",
            "TUSU": "148,313",
            "TUYUL": "63.5",
            "GPYUL": "99.98%",
            "name": 2606,
            "nametxt": "동래구",
            "data": [
                {
                    "value": 43.38,
                    "name": "탁영일",
                    "party": "더불어민주당",
                    "pyo": 63476,
                    "itemStyle": {
                        "color": "#152484"
                    }
                },
                {
                    "value": 56.61,
                    "name": "장준용",
                    "party": "국민의힘",
                    "pyo": 82847,
                    "itemStyle": {
                        "color": "#E61E2B"
                    }
                }
            ],
            "HUBO01": "탁영일",
            "JD01": "더불어민주당",
            "DUGSU01": "63,476",
            "DUGYUL01": "43.38",
            "HUBO02": "장준용",
            "JD02": "국민의힘",
            "DUGSU02": "82,847",
            "DUGYUL02": "56.61",
            "WINNUM": 2,
            "WINDUGSU": "82,847",
            "WINDUGYUL": "56.61",
            "WINHUBO": "장준용",
            "WINJD": "국민의힘",
            "SECNUM": 1,
            "SECDUGSU": "63,476",
            "SECDUGYUL": "43.38",
            "SECHUBO": "탁영일",
            "SECJD": "더불어민주당",
            "DUGYULCHA": "13.23",
            "DUGSUCHA": "19,371",
            "value": 2
        },
        {
            "SDID": 2600,
            "SDNAME": "부산광역시",
            "SGGID": "4260700",
            "SGGNAME": "남구",
            "WIWID": 2607,
            "WIWNAME": "남구",
            "SUNSU": "224,406",
            "TUSU": "141,140",
            "TUYUL": "62.9",
            "GPYUL": "99.97%",
            "name": 2607,
            "nametxt": "남구",
            "data": [
                {
                    "value": 50.43,
                    "name": "박재범",
                    "party": "더불어민주당",
                    "pyo": 70160,
                    "itemStyle": {
                        "color": "#152484"
                    }
                },
                {
                    "value": 49.56,
                    "name": "김광명",
                    "party": "국민의힘",
                    "pyo": 68957,
                    "itemStyle": {
                        "color": "#E61E2B"
                    }
                }
            ],
            "HUBO01": "박재범",
            "JD01": "더불어민주당",
            "DUGSU01": "70,160",
            "DUGYUL01": "50.43",
            "HUBO02": "김광명",
            "JD02": "국민의힘",
            "DUGSU02": "68,957",
            "DUGYUL02": "49.56",
            "WINNUM": 1,
            "WINDUGSU": "70,160",
            "WINDUGYUL": "50.43",
            "WINHUBO": "박재범",
            "WINJD": "더불어민주당",
            "SECNUM": 2,
            "SECDUGSU": "68,957",
            "SECDUGYUL": "49.56",
            "SECHUBO": "김광명",
            "SECJD": "국민의힘",
            "DUGYULCHA": "0.87",
            "DUGSUCHA": "1,203",
            "value": 1
        },
        {
            "SDID": 2600,
            "SDNAME": "부산광역시",
            "SGGID": "4260800",
            "SGGNAME": "북구",
            "WIWID": 2608,
            "WIWNAME": "북구",
            "SUNSU": "232,141",
            "TUSU": "146,070",
            "TUYUL": "62.9",
            "GPYUL": "89.67%",
            "name": 2608,
            "nametxt": "북구",
            "data": [
                {
                    "value": 52.83,
                    "name": "정명희",
                    "party": "더불어민주당",
                    "pyo": 74665,
                    "itemStyle": {
                        "color": "#152484"
                    }
                },
                {
                    "value": 47.16,
                    "name": "오태원",
                    "party": "국민의힘",
                    "pyo": 66661,
                    "itemStyle": {
                        "color": "#E61E2B"
                    }
                }
            ],
            "HUBO01": "정명희",
            "JD01": "더불어민주당",
            "DUGSU01": "74,665",
            "DUGYUL01": "52.83",
            "HUBO02": "오태원",
            "JD02": "국민의힘",
            "DUGSU02": "66,661",
            "DUGYUL02": "47.16",
            "WINNUM": 1,
            "WINDUGSU": "74,665",
            "WINDUGYUL": "52.83",
            "WINHUBO": "정명희",
            "WINJD": "더불어민주당",
            "SECNUM": 2,
            "SECDUGSU": "66,661",
            "SECDUGYUL": "47.16",
            "SECHUBO": "오태원",
            "SECJD": "국민의힘",
            "DUGYULCHA": "5.67",
            "DUGSUCHA": "8,004",
            "value": 1
        },
        {
            "SDID": 2600,
            "SDNAME": "부산광역시",
            "SGGID": "4260900",
            "SGGNAME": "해운대구",
            "WIWID": 2609,
            "WIWNAME": "해운대구",
            "SUNSU": "323,439",
            "TUSU": "198,831",
            "TUYUL": "61.5",
            "GPYUL": "99.97%",
            "name": 2609,
            "nametxt": "해운대구",
            "data": [
                {
                    "value": 48.97,
                    "name": "홍순헌",
                    "party": "더불어민주당",
                    "pyo": 95849,
                    "itemStyle": {
                        "color": "#152484"
                    }
                },
                {
                    "value": 51.02,
                    "name": "김성수",
                    "party": "국민의힘",
                    "pyo": 99851,
                    "itemStyle": {
                        "color": "#E61E2B"
                    }
                }
            ],
            "HUBO01": "홍순헌",
            "JD01": "더불어민주당",
            "DUGSU01": "95,849",
            "DUGYUL01": "48.97",
            "HUBO02": "김성수",
            "JD02": "국민의힘",
            "DUGSU02": "99,851",
            "DUGYUL02": "51.02",
            "WINNUM": 2,
            "WINDUGSU": "99,851",
            "WINDUGYUL": "51.02",
            "WINHUBO": "김성수",
            "WINJD": "국민의힘",
            "SECNUM": 1,
            "SECDUGSU": "95,849",
            "SECDUGYUL": "48.97",
            "SECHUBO": "홍순헌",
            "SECJD": "더불어민주당",
            "DUGYULCHA": "2.05",
            "DUGSUCHA": "4,002",
            "value": 2
        },
        {
            "SDID": 2600,
            "SDNAME": "부산광역시",
            "SGGID": "4261100",
            "SGGNAME": "사하구",
            "WIWID": 2611,
            "WIWNAME": "사하구",
            "SUNSU": "253,639",
            "TUSU": "112,112",
            "TUYUL": "44.2",
            "GPYUL": "74.30%",
            "name": 2611,
            "nametxt": "사하구",
            "data": [
                {
                    "value": 53.48,
                    "name": "김태석",
                    "party": "더불어민주당",
                    "pyo": 58835,
                    "itemStyle": {
                        "color": "#152484"
                    }
                },
                {
                    "value": 46.51,
                    "name": "김척수",
                    "party": "국민의힘",
                    "pyo": 51160,
                    "itemStyle": {
                        "color": "#E61E2B"
                    }
                }
            ],
            "HUBO01": "김태석",
            "JD01": "더불어민주당",
            "DUGSU01": "58,835",
            "DUGYUL01": "53.48",
            "HUBO02": "김척수",
            "JD02": "국민의힘",
            "DUGSU02": "51,160",
            "DUGYUL02": "46.51",
            "WINNUM": 1,
            "WINDUGSU": "58,835",
            "WINDUGYUL": "53.48",
            "WINHUBO": "김태석",
            "WINJD": "더불어민주당",
            "SECNUM": 2,
            "SECDUGSU": "51,160",
            "SECDUGYUL": "46.51",
            "SECHUBO": "김척수",
            "SECJD": "국민의힘",
            "DUGYULCHA": "6.97",
            "DUGSUCHA": "7,675",
            "value": 1
        },
        {
            "SDID": 2600,
            "SDNAME": "부산광역시",
            "SGGID": "4261200",
            "SGGNAME": "금정구",
            "WIWID": 2612,
            "WIWNAME": "금정구",
            "SUNSU": "186,469",
            "TUSU": "104,915",
            "TUYUL": "56.3",
            "GPYUL": "89.64%",
            "name": 2612,
            "nametxt": "금정구",
            "data": [
                {
                    "value": 42.61,
                    "name": "김경지",
                    "party": "더불어민주당",
                    "pyo": 43910,
                    "itemStyle": {
                        "color": "#152484"
                    }
                },
                {
                    "value": 53.83,
                    "name": "윤일현",
                    "party": "국민의힘",
                    "pyo": 55470,
                    "itemStyle": {
                        "color": "#E61E2B"
                    }
                },
                {
                    "value": 1.4,
                    "name": "박용찬",
                    "party": "조국혁신당",
                    "pyo": 1444,
                    "itemStyle": {
                        "color": "#004099"
                    }
                },
                {
                    "value": 2.15,
                    "name": "최봉환",
                    "party": "개혁신당",
                    "pyo": 2220,
                    "itemStyle": {
                        "color": "#FF7920"
                    }
                }
            ],
            "HUBO01": "김경지",
            "JD01": "더불어민주당",
            "DUGSU01": "43,910",
            "DUGYUL01": "42.61",
            "HUBO02": "윤일현",
            "JD02": "국민의힘",
            "DUGSU02": "55,470",
            "DUGYUL02": "53.83",
            "HUBO03": "박용찬",
            "JD03": "조국혁신당",
            "DUGSU03": "1,444",
            "DUGYUL03": "1.40",
            "HUBO04": "최봉환",
            "JD04": "개혁신당",
            "DUGSU04": "2,220",
            "DUGYUL04": "2.15",
            "WINNUM": 2,
            "WINDUGSU": "55,470",
            "WINDUGYUL": "53.83",
            "WINHUBO": "윤일현",
            "WINJD": "국민의힘",
            "SECNUM": 1,
            "SECDUGSU": "43,910",
            "SECDUGYUL": "42.61",
            "SECHUBO": "김경지",
            "SECJD": "더불어민주당",
            "DUGYULCHA": "11.22",
            "DUGSUCHA": "11,560",
            "value": 2
        },
        {
            "SDID": 2600,
            "SDNAME": "부산광역시",
            "SGGID": "4261300",
            "SGGNAME": "강서구",
            "WIWID": 2613,
            "WIWNAME": "강서구",
            "SUNSU": "120,347",
            "TUSU": "57,242",
            "TUYUL": "47.6",
            "GPYUL": "76.43%",
            "name": 2613,
            "nametxt": "강서구",
            "data": [
                {
                    "value": 53.79,
                    "name": "박상준",
                    "party": "더불어민주당",
                    "pyo": 30386,
                    "itemStyle": {
                        "color": "#152484"
                    }
                },
                {
                    "value": 46.2,
                    "name": "김형찬",
                    "party": "국민의힘",
                    "pyo": 26104,
                    "itemStyle": {
                        "color": "#E61E2B"
                    }
                }
            ],
            "HUBO01": "박상준",
            "JD01": "더불어민주당",
            "DUGSU01": "30,386",
            "DUGYUL01": "53.79",
            "HUBO02": "김형찬",
            "JD02": "국민의힘",
            "DUGSU02": "26,104",
            "DUGYUL02": "46.20",
            "WINNUM": 1,
            "WINDUGSU": "30,386",
            "WINDUGYUL": "53.79",
            "WINHUBO": "박상준",
            "WINJD": "더불어민주당",
            "SECNUM": 2,
            "SECDUGSU": "26,104",
            "SECDUGYUL": "46.20",
            "SECHUBO": "김형찬",
            "SECJD": "국민의힘",
            "DUGYULCHA": "7.59",
            "DUGSUCHA": "4,282",
            "value": 1
        },
        {
            "SDID": 2600,
            "SDNAME": "부산광역시",
            "SGGID": "4261400",
            "SGGNAME": "연제구",
            "WIWID": 2614,
            "WIWNAME": "연제구",
            "SUNSU": "185,579",
            "TUSU": "118,703",
            "TUYUL": "64.0",
            "GPYUL": "99.82%",
            "name": 2614,
            "nametxt": "연제구",
            "data": [
                {
                    "value": 56.34,
                    "name": "주석수",
                    "party": "국민의힘",
                    "pyo": 60915,
                    "itemStyle": {
                        "color": "#E61E2B"
                    }
                },
                {
                    "value": 43.65,
                    "name": "노정현",
                    "party": "진보당",
                    "pyo": 47196,
                    "itemStyle": {
                        "color": "#D6001C"
                    }
                }
            ],
            "HUBO01": "주석수",
            "JD01": "국민의힘",
            "DUGSU01": "60,915",
            "DUGYUL01": "56.34",
            "HUBO02": "노정현",
            "JD02": "진보당",
            "DUGSU02": "47,196",
            "DUGYUL02": "43.65",
            "WINNUM": 1,
            "WINDUGSU": "60,915",
            "WINDUGYUL": "56.34",
            "WINHUBO": "주석수",
            "WINJD": "국민의힘",
            "SECNUM": 2,
            "SECDUGSU": "47,196",
            "SECDUGYUL": "43.65",
            "SECHUBO": "노정현",
            "SECJD": "진보당",
            "DUGYULCHA": "12.69",
            "DUGSUCHA": "13,719",
            "value": 2
        },
        {
            "SDID": 2600,
            "SDNAME": "부산광역시",
            "SGGID": "4261500",
            "SGGNAME": "수영구",
            "WIWID": 2615,
            "WIWNAME": "수영구",
            "SUNSU": "152,304",
            "TUSU": "91,431",
            "TUYUL": "60.0",
            "GPYUL": "99.98%",
            "name": 2615,
            "nametxt": "수영구",
            "data": [
                {
                    "value": 38.29,
                    "name": "김진",
                    "party": "더불어민주당",
                    "pyo": 34542,
                    "itemStyle": {
                        "color": "#152484"
                    }
                },
                {
                    "value": 57.0,
                    "name": "강성태",
                    "party": "국민의힘",
                    "pyo": 51416,
                    "itemStyle": {
                        "color": "#E61E2B"
                    }
                },
                {
                    "value": 4.7,
                    "name": "황진수",
                    "party": "무소속",
                    "pyo": 4240,
                    "itemStyle": {
                        "color": "#8b8b8b"
                    }
                }
            ],
            "HUBO01": "김진",
            "JD01": "더불어민주당",
            "DUGSU01": "34,542",
            "DUGYUL01": "38.29",
            "HUBO02": "강성태",
            "JD02": "국민의힘",
            "DUGSU02": "51,416",
            "DUGYUL02": "57.00",
            "HUBO03": "황진수",
            "JD03": "무소속",
            "DUGSU03": "4,240",
            "DUGYUL03": "4.70",
            "WINNUM": 2,
            "WINDUGSU": "51,416",
            "WINDUGYUL": "57.00",
            "WINHUBO": "강성태",
            "WINJD": "국민의힘",
            "SECNUM": 1,
            "SECDUGSU": "34,542",
            "SECDUGYUL": "38.29",
            "SECHUBO": "김진",
            "SECJD": "더불어민주당",
            "DUGYULCHA": "18.71",
            "DUGSUCHA": "16,874",
            "value": 2
        },
        {
            "SDID": 2600,
            "SDNAME": "부산광역시",
            "SGGID": "4261600",
            "SGGNAME": "사상구",
            "WIWID": 2616,
            "WIWNAME": "사상구",
            "SUNSU": "175,616",
            "TUSU": "70,756",
            "TUYUL": "40.3",
            "GPYUL": "66.07%",
            "name": 2616,
            "nametxt": "사상구",
            "data": [
                {
                    "value": 48.96,
                    "name": "서태경",
                    "party": "더불어민주당",
                    "pyo": 33906,
                    "itemStyle": {
                        "color": "#152484"
                    }
                },
                {
                    "value": 41.8,
                    "name": "이대훈",
                    "party": "국민의힘",
                    "pyo": 28946,
                    "itemStyle": {
                        "color": "#E61E2B"
                    }
                },
                {
                    "value": 9.23,
                    "name": "조병길",
                    "party": "무소속",
                    "pyo": 6396,
                    "itemStyle": {
                        "color": "#8b8b8b"
                    }
                }
            ],
            "HUBO01": "서태경",
            "JD01": "더불어민주당",
            "DUGSU01": "33,906",
            "DUGYUL01": "48.96",
            "HUBO02": "이대훈",
            "JD02": "국민의힘",
            "DUGSU02": "28,946",
            "DUGYUL02": "41.80",
            "HUBO03": "조병길",
            "JD03": "무소속",
            "DUGSU03": "6,396",
            "DUGYUL03": "9.23",
            "WINNUM": 1,
            "WINDUGSU": "33,906",
            "WINDUGYUL": "48.96",
            "WINHUBO": "서태경",
            "WINJD": "더불어민주당",
            "SECNUM": 2,
            "SECDUGSU": "28,946",
            "SECDUGYUL": "41.80",
            "SECHUBO": "이대훈",
            "SECJD": "국민의힘",
            "DUGYULCHA": "7.16",
            "DUGSUCHA": "4,960",
            "value": 1
        },
        {
            "SDID": 2600,
            "SDNAME": "부산광역시",
            "SGGID": "4261000",
            "SGGNAME": "기장군",
            "WIWID": 2610,
            "WIWNAME": "기장군",
            "SUNSU": "146,538",
            "TUSU": "82,946",
            "TUYUL": "56.6",
            "GPYUL": "94.83%",
            "name": 2610,
            "nametxt": "기장군",
            "data": [
                {
                    "value": 44.5,
                    "name": "우성빈",
                    "party": "더불어민주당",
                    "pyo": 36332,
                    "itemStyle": {
                        "color": "#152484"
                    }
                },
                {
                    "value": 42.17,
                    "name": "정명시",
                    "party": "국민의힘",
                    "pyo": 34434,
                    "itemStyle": {
                        "color": "#E61E2B"
                    }
                },
                {
                    "value": 1.78,
                    "name": "정진백",
                    "party": "조국혁신당",
                    "pyo": 1461,
                    "itemStyle": {
                        "color": "#004099"
                    }
                },
                {
                    "value": 11.53,
                    "name": "김쌍우",
                    "party": "무소속",
                    "pyo": 9416,
                    "itemStyle": {
                        "color": "#8b8b8b"
                    }
                }
            ],
            "HUBO01": "우성빈",
            "JD01": "더불어민주당",
            "DUGSU01": "36,332",
            "DUGYUL01": "44.50",
            "HUBO02": "정명시",
            "JD02": "국민의힘",
            "DUGSU02": "34,434",
            "DUGYUL02": "42.17",
            "HUBO03": "정진백",
            "JD03": "조국혁신당",
            "DUGSU03": "1,461",
            "DUGYUL03": "1.78",
            "HUBO04": "김쌍우",
            "JD04": "무소속",
            "DUGSU04": "9,416",
            "DUGYUL04": "11.53",
            "WINNUM": 1,
            "WINDUGSU": "36,332",
            "WINDUGYUL": "44.50",
            "WINHUBO": "우성빈",
            "WINJD": "더불어민주당",
            "SECNUM": 2,
            "SECDUGSU": "34,434",
            "SECDUGYUL": "42.17",
            "SECHUBO": "정명시",
            "SECJD": "국민의힘",
            "DUGYULCHA": "2.33",
            "DUGSUCHA": "1,898",
            "value": 1
        }
    ]
}